LICENSE
README.md
pyproject.toml
setup.py
src/jinny/__init__.py
src/jinny/error.html
src/jinny/jinny.py
src/jinny/version
src/jinny.egg-info/PKG-INFO
src/jinny.egg-info/SOURCES.txt
src/jinny.egg-info/dependency_links.txt
src/jinny.egg-info/entry_points.txt
src/jinny.egg-info/requires.txt
src/jinny.egg-info/top_level.txt
src/jinny/imports/__init__.py
src/jinny/imports/filter_extensions.py
src/jinny/imports/global_extensions.py
src/jinny/imports/jinny_unsafe.py