Metadata-Version: 2.1
Name: jinny
Version: 2.2.0
Summary: A practical templating tool for Jinja templates
Home-page: 
Author: smasherofallthings
Author-email: bots@trulydigital.net
License: GPLv3
Project-URL: Github, https://github.com/smashthings/jinny
Project-URL: Gitlab, https://gitlab.com/scripteddog/jinny
Keywords: jinja,template,jinja2,kubernetes,cli
Classifier: Programming Language :: Python :: 3
Classifier: License :: OSI Approved :: GNU General Public License v3 (GPLv3)
Classifier: Operating System :: POSIX :: Other
Requires-Python: >=3.6
License-File: LICENSE
